<annotation>
	<folder>hand_data_2</folder>
	<filename>2_pic00492.jpg</filename>
	<path>/Users/Soubhi/Desktop/hand_data_2/pic00492.jpg</path>
	<source>
		<database>Unknown</database>
	</source>
	<size>
		<width>800</width>
		<height>600</height>
		<depth>3</depth>
	</size>
	<segmented>0</segmented>
	<object>
		<name>0-hand</name>
		<pose>Unspecified</pose>
		<truncated>1</truncated>
		<difficult>0</difficult>
		<bndbox>
			<xmin>342</xmin>
			<ymin>1</ymin>
			<xmax>563</xmax>
			<ymax>311</ymax>
		</bndbox>
	</object>
</annotation>