<annotation>
	<folder>data_6</folder>
	<filename>996_pic00092.jpg</filename>
	<path>/Users/Soubhi/Desktop/data_6/996_pic00092.jpg</path>
	<source>
		<database>Unknown</database>
	</source>
	<size>
		<width>800</width>
		<height>600</height>
		<depth>3</depth>
	</size>
	<segmented>0</segmented>
	<object>
		<name>0-hand</name>
		<pose>Unspecified</pose>
		<truncated>0</truncated>
		<difficult>0</difficult>
		<bndbox>
			<xmin>78</xmin>
			<ymin>196</ymin>
			<xmax>220</xmax>
			<ymax>417</ymax>
		</bndbox>
	</object>
</annotation>
