<annotation>
	<folder>hand_data_2</folder>
	<filename>2_pic00120.jpg</filename>
	<path>/Users/Soubhi/Desktop/hand_data_2/pic00120.jpg</path>
	<source>
		<database>Unknown</database>
	</source>
	<size>
		<width>800</width>
		<height>600</height>
		<depth>3</depth>
	</size>
	<segmented>0</segmented>
	<object>
		<name>5-hand</name>
		<pose>Unspecified</pose>
		<truncated>0</truncated>
		<difficult>0</difficult>
		<bndbox>
			<xmin>325</xmin>
			<ymin>105</ymin>
			<xmax>626</xmax>
			<ymax>508</ymax>
		</bndbox>
	</object>
</annotation>